{
  "name": "Repair Melee Weapons",
  "type": "script",
  "scope": "global",
  "author": "ZJyAmf2sKocHG1ud",
  "img": "icons/skills/trades/smithing-tongs-metal-red.webp",
  "command": "const api = game.modules.get(\"forien-armoury\")?.api.itemRepair;\n\nif (api && scope.buyer && scope.userId) {\n  api.checkInventoryForDamage(scope.buyer, {\n    paid: true,\n    type: \"weapons\",\n    subtype: \"basic,cavalry,fencing,brawling,flail,parry,polearm,twohanded\",\n    user: scope.userId\n  });\n}",
  "folder": "PrF8OmDhD6LXHdz1",
  "ownership": {
    "default": 0,
    "ZJyAmf2sKocHG1ud": 3
  },
  "flags": {
    "core": {}
  },
  "_stats": {
    "systemId": "wfrp4e",
    "systemVersion": "6.6.0",
    "coreVersion": "12.327",
    "createdTime": 1690506986386,
    "modifiedTime": 1690870315593,
    "lastModifiedBy": "ZJyAmf2sKocHG1ud",
    "compendiumSource": null,
    "duplicateSource": null
  },
  "_id": "SePhG2mBoIou48Iq",
  "sort": 100000,
  "_key": "!macros!SePhG2mBoIou48Iq"
}
